muxec/__init__.py
muxec/consts.py
muxec/errors.py
muxec/main.py
muxec/panes.py
muxec/run.py
muxec/state.py
muxec/util.py
muxec-0.1.14.dist-info/LICENSE
muxec-0.1.14.dist-info/METADATA
muxec-0.1.14.dist-info/WHEEL
muxec-0.1.14.dist-info/entry_points.txt
muxec-0.1.14.dist-info/top_level.txt
muxec-0.1.14.dist-info/RECORD
