Metadata-Version: 2.1
Name: muxec
Version: 0.1.14
Summary: Multiplexed Exec Tool
Home-page: https://github.com/ReallyLiri/muxec
Author: ReallyLiri
Author-email: reallyliri@gmail.com
License: UNKNOWN
Keywords: mux multiplex exec execute xargs shell parallel
Platform: UNKNOWN
Classifier: Programming Language :: Python :: 3
Classifier: Operating System :: OS Independent
Requires-Python: >=3.6
License-File: LICENSE
